Workbook

Sheet Summary
A1: Migration mapping — summary
A2: Counts are formulas over the Mapping sheet. Source: migration/migration-mapping.csv (scripts/migration/build_mapping.py).
A4: Action | B4: Items | C4: MB
A5: Migrate | B5: =COUNTIF(Mapping!$H$2:$H$2146,A5) -> 231 | C5: =SUMIF(Mapping!$H$2:$H$2146,A5,Mapping!$D$2:$D$2146)/1000000 -> 69.133672
A6: Rename | B6: =COUNTIF(Mapping!$H$2:$H$2146,A6) -> 49 | C6: =SUMIF(Mapping!$H$2:$H$2146,A6,Mapping!$D$2:$D$2146)/1000000 -> 11.697424
A7: Extract | B7: =COUNTIF(Mapping!$H$2:$H$2146,A7) -> 1133 | C7: =SUMIF(Mapping!$H$2:$H$2146,A7,Mapping!$D$2:$D$2146)/1000000 -> 175.17837
A8: Convert | B8: =COUNTIF(Mapping!$H$2:$H$2146,A8) -> 26 | C8: =SUMIF(Mapping!$H$2:$H$2146,A8,Mapping!$D$2:$D$2146)/1000000 -> 5.084139
A9: Archive | B9: =COUNTIF(Mapping!$H$2:$H$2146,A9) -> 5 | C9: =SUMIF(Mapping!$H$2:$H$2146,A9,Mapping!$D$2:$D$2146)/1000000 -> 11.959312
A10: Duplicate | B10: =COUNTIF(Mapping!$H$2:$H$2146,A10) -> 389 | C10: =SUMIF(Mapping!$H$2:$H$2146,A10,Mapping!$D$2:$D$2146)/1000000 -> 105.49736
A11: Exclude | B11: =COUNTIF(Mapping!$H$2:$H$2146,A11) -> 298 | C11: =SUMIF(Mapping!$H$2:$H$2146,A11,Mapping!$D$2:$D$2146)/1000000 -> 10.483076
A12: Container | B12: =COUNTIF(Mapping!$H$2:$H$2146,A12) -> 14 | C12: =SUMIF(Mapping!$H$2:$H$2146,A12,Mapping!$D$2:$D$2146)/1000000 -> 130.05044
A13: Total | B13: =SUM(B5:B12) -> 2145 | C13: =SUM(C5:C12) -> 519.08379
A15: Category | B15: Items | C15: MB
A16: Ready | B16: =COUNTIF(Mapping!$I$2:$I$2146,A16) -> 1426 | C16: =SUMIF(Mapping!$I$2:$I$2146,A16,Mapping!$D$2:$D$2146)/1000000 -> 382.52318
A17: Needs Review | B17: =COUNTIF(Mapping!$I$2:$I$2146,A17) -> 23 | C17: =SUMIF(Mapping!$I$2:$I$2146,A17,Mapping!$D$2:$D$2146)/1000000 -> 15.510094
A18: Security Concern | B18: =COUNTIF(Mapping!$I$2:$I$2146,A18) -> 6 | C18: =SUMIF(Mapping!$I$2:$I$2146,A18,Mapping!$D$2:$D$2146)/1000000 -> 0.784122
A19: Duplicate | B19: =COUNTIF(Mapping!$I$2:$I$2146,A19) -> 391 | C19: =SUMIF(Mapping!$I$2:$I$2146,A19,Mapping!$D$2:$D$2146)/1000000 -> 109.62648
A20: Obsolete | B20: =COUNTIF(Mapping!$I$2:$I$2146,A20) -> 299 | C20: =SUMIF(Mapping!$I$2:$I$2146,A20,Mapping!$D$2:$D$2146)/1000000 -> 10.639914
A21: Total | B21: =SUM(B16:B20) -> 2145 | C21: =SUM(C16:C20) -> 519.08379
A23: Storage | B23: Items | C23: MB
A24: git | B24: =COUNTIF(Mapping!$J$2:$J$2146,A24) -> 1120 | C24: =SUMIF(Mapping!$J$2:$J$2146,A24,Mapping!$D$2:$D$2146)/1000000 -> 78.912332
A25: git-lfs | B25: =COUNTIF(Mapping!$J$2:$J$2146,A25) -> 324 | C25: =SUMIF(Mapping!$J$2:$J$2146,A25,Mapping!$D$2:$D$2146)/1000000 -> 194.14058
A26: Total | B26: =SUM(B24:B25) -> 1444 | C26: =SUM(C24:C25) -> 273.05292

Sheet Mapping
A1: source_path | B1: archive_member | C1: sha256 | D1: size_bytes | E1: course_code | F1: content_type | G1: target_path | H1: action | I1: category | J1: storage | K1: notes
A2: AI Engineer Track/AI Engineering Capstone — Production GenAI System/INSTRUCTOR_PACKAGE.md | C2: 9e74406ad5697e6d6c7124571d93630badfc2fd3e66c972a2e74ea78cebe144c | D2: 169710 | E2: SDA-AIE-390 | F2: Instructor guide | G2: catalog/ai-engineer/SDA-AIE-390-ai-engineering-capstone-production-genai-system/instructor-guide.md | H2: Convert | I2: Ready | J2: git | K2: Body preserved verbatim under a governance header
A3: AI Engineer Track/AI Performance, Scalability and Cost Optimization/INSTRUCTOR_PACKAGE.md | C3: 6718a403aa64450f21f80ad3831694663ea0f3c124c25e37abf9d326c847886f | D3: 174645 | E3: SDA-AIE-314 | F3: Instructor guide | G3: catalog/ai-engineer/SDA-AIE-314-ai-performance-scalability-and-cost-optimization/instructor-guide.md | H3: Convert | I3: Ready | J3: git | K3: Body preserved verbatim under a governance header
A4: AI Engineer Track/AI Security, Guardrails and Red Teaming/INSTRUCTOR_PACKAGE.md | C4: 5327db71cbf725292a33c1b10a2639df52c0ec8b3940753adc13ee530e78ccba | D4: 169683 | E4: SDA-AIE-313 | F4: Instructor guide | G4: catalog/ai-engineer/SDA-AIE-313-ai-security-guardrails-and-red-teaming/instructor-guide.md | H4: Convert | I4: Ready | J4: git | K4: Body preserved verbatim under a governance header
A5: AI Engineer Track/Advanced Agentic AI Systems Engineering/01_Training_Deck/SDA-AIE-311_Agentic_AI_Systems_Engineering_Deck.pdf | C5: 0f677a22fbace5ab416206900145bb94018f1162c17bfe097b3958063b893855 | D5: 2620813 | E5: SDA-AIE-311 | F5: Slides | G5: catalog/ai-engineer/SDA-AIE-311-agentic-ai-systems-engineering/slides/SDA-AIE-311_Agentic_AI_Systems_Engineering_Deck.pdf | H5: Migrate | I5: Ready | J5: git-lfs
A6: AI Engineer Track/Advanced Agentic AI Systems Engineering/01_Training_Deck/SDA-AIE-311_Agentic_AI_Systems_Engineering_Deck.pptx | C6: 7205be374a1ff9475c25efe2a51114323bc10dfd09900c005b3aba97759072f3 | D6: 6972619 | E6: SDA-AIE-311 | F6: Slides | G6: catalog/ai-engineer/SDA-AIE-311-agentic-ai-systems-engineering/slides/SDA-AIE-311_Agentic_AI_Systems_Engineering_Deck.pptx | H6: Migrate | I6: Ready | J6: git-lfs
A7: AI Engineer Track/Advanced Agentic AI Systems Engineering/02_Programme_Guides/ASSESSMENT_PACK.md | C7: bab08e0c7cd32cc4825c36d1055c9aa53766a813ed75cd4ab50ccc2a842cf3d9 | D7: 17776 | E7: SDA-AIE-311 | F7: Assessment | G7: catalog/ai-engineer/SDA-AIE-311-agentic-ai-systems-engineering/assessments/ASSESSMENT_PACK.md | H7: Migrate | I7: Ready | J7: git
A8: AI Engineer Track/Advanced Agentic AI Systems Engineering/02_Programme_Guides/INSTRUCTOR_DELIVERY_GUIDE.md | C8: 8a11598495f6f08dd90759eafcb0bdab2f642bb5195945eac6196e75304630e9 | D8: 27808 | E8: SDA-AIE-311 | F8: Instructor guide (delivery) | G8: catalog/ai-engineer/SDA-AIE-311-agentic-ai-systems-engineering/resources/instructor/INSTRUCTOR_DELIVERY_GUIDE.md | H8: Migrate | I8: Ready | J8: git
A9: AI Engineer Track/Advanced Agentic AI Systems Engineering/02_Programme_Guides/PARTICIPANT_HANDBOOK.md | C9: 4119c3df847bc214fd19dc212de3ae01a23f7de865a1074900935e29c0aa469f | D9: 40515 | E9: SDA-AIE-311 | F9: Participant material | G9: catalog/ai-engineer/SDA-AIE-311-agentic-ai-systems-engineering/resources/participant/PARTICIPANT_HANDBOOK.md | H9: Migrate | I9: Ready | J9: git
A10: AI Engineer Track/Advanced Agentic AI Systems Engineering/02_Programme_Guides/PROGRAMME_OVERVIEW.md | C10: c5ace92269972aeb5a67c0d1fd37288ceca00bee188873bbc53f0f9ddcb1f96b | D10: 9472 | E10: SDA-AIE-311 | F10: Programme guide | G10: catalog/ai-engineer/SDA-AIE-311-agentic-ai-systems-engineering/resources/PROGRAMME_OVERVIEW.md | H10: Migrate | I10: Ready | J10: git
A11: AI Engineer Track/Advanced Agentic AI Systems Engineering/02_Programme_Guides/RESOURCES.md | C11: 3162834b9a74e95887d884e7a921a2a037f104478c83299ea60af1dd6382d7af | D11: 22183 | E11: SDA-AIE-311 | F11: Programme guide | G11: catalog/ai-engineer/SDA-AIE-311-agentic-ai-systems-engineering/resources/RESOURCES.md | H11: Migrate | I11: Ready | J11: git
A12: AI Engineer Track/Advanced Agentic AI Systems Engineering/02_Programme_Guides/SETUP_GUIDE.md | C12: d7317ee296db14eb536b3a5fe2e20b1803e22f87f77f9949136601976c3445d8 | D12: 14191 | E12: SDA-AIE-311 | F12: Programme guide | G12: catalog/ai-engineer/SDA-AIE-311-agentic-ai-systems-engineering/resources/SETUP_GUIDE.md | H12: Migrate | I12: Ready | J12: git
A13: AI Engineer Track/Advanced Agentic AI Systems Engineering/02_Programme_Guides/VISUAL_ASSET_BRIEF.md | C13: 14709e59820229251101ebed710b53f1bac65972ab3b3eaf2f4f9920e6643394 | D13: 25085 | E13: SDA-AIE-311 | F13: Programme guide | G13: catalog/ai-engineer/SDA-AIE-311-agentic-ai-systems-engineering/resources/VISUAL_ASSET_BRIEF.md | H13: Migrate | I13: Ready | J13: git
A14: AI Engineer Track/Advanced Agentic AI Systems Engineering/03_Course_Repository/tawseel-agentic-ai.zip | C14: 2fc08e6b2cffd702c9863bd133c6c110f54319628ca9c50ed9b2f1af26f016d6 | D14: 1161637 | E14: SDA-AIE-311 | F14: Archive | H14: Container | I14: Ready | K14: Members classified individually
A15: AI Engineer Track/Advanced Agentic AI Systems Engineering/03_Course_Repository/tawseel-agentic-ai.zip | B15: tawseel-agentic-ai/.dockerignore | C15: 23c3bda71253c49714e08e4ef28cfe359f173c44b143fc47c5f9719f31842725 | D15: 590 | E15: SDA-AIE-311 | F15: Lab repository | G15: catalog/ai-engineer/SDA-AIE-311-agentic-ai-systems-engineering/labs/tawseel-agentic-ai/.dockerignore | H15: Extract | I15: Ready | J15: git
A16: AI Engineer Track/Advanced Agentic AI Systems Engineering/03_Course_Repository/tawseel-agentic-ai.zip | B16: tawseel-agentic-ai/.env.example | C16: 9ce666efe30536bca9f9b66dd60404292a6eb3b9fe8678864d05772dc893fa14 | D16: 2070 | E16: SDA-AIE-311 | F16: Lab repository | G16: catalog/ai-engineer/SDA-AIE-311-agentic-ai-systems-engineering/labs/tawseel-agentic-ai/.env.example | H16: Extract | I16: Ready | J16: git
A17: AI Engineer Track/Advanced Agentic AI Systems Engineering/03_Course_Repository/tawseel-agentic-ai.zip | B17: tawseel-agentic-ai/.github/workflows/ci.yml | C17: 104be6860c06099cdcc0939b55aa9f835e4600322c88aaaf319bc5a143f870a8 | D17: 7675 | E17: SDA-AIE-311 | F17: Lab repository | G17: catalog/ai-engineer/SDA-AIE-311-agentic-ai-systems-engineering/labs/tawseel-agentic-ai/.github/workflows/ci.yml | H17: Extract | I17: Ready | J17: git
A18: AI Engineer Track/Advanced Agentic AI Systems Engineering/03_Course_Repository/tawseel-agentic-ai.zip | B18: tawseel-agentic-ai/.gitignore | C18: 6d7e9097d691c03851a32f26d0edc7ca6b9b16b50eaa29d0af2e52c8233e5d9e | D18: 1286 | E18: SDA-AIE-311 | F18: Lab repository | G18: catalog/ai-engineer/SDA-AIE-311-agentic-ai-systems-engineering/labs/tawseel-agentic-ai/.gitignore | H18: Extract | I18: Ready | J18: git
A19: AI Engineer Track/Advanced Agentic AI Systems Engineering/03_Course_Repository/tawseel-agentic-ai.zip | B19: tawseel-agentic-ai/CONTRIBUTING.md | C19: 5a7600bb500bf3bc302c8eccbc2d130cf5d774836be5ab1283b44b4041d26c04 | D19: 3728 | E19: SDA-AIE-311 | F19: Lab repository | G19: catalog/ai-engineer/SDA-AIE-311-agentic-ai-systems-engineering/labs/tawseel-agentic-ai/CONTRIBUTING.md | H19: Extract | I19: Ready | J19: git
A20: AI Engineer Track/Advanced Agentic AI Systems Engineering/03_Course_Repository/tawseel-agentic-ai.zip | B20: tawseel-agentic-ai/Dockerfile | C20: 1df13ec119fc3ca476fe83c0634dce31bd29c7b1582efe55f386d420c6282b82 | D20: 1911 | E20: SDA-AIE-311 | F20: Lab repository | G20: catalog/ai-engineer/SDA-AIE-311-agentic-ai-systems-engineering/labs/tawseel-agentic-ai/Dockerfile | H20: Extract | I20: Ready | J20: git
A21: AI Engineer Track/Advanced Agentic AI Systems Engineering/03_Course_Repository/tawseel-agentic-ai.zip | B21: tawseel-agentic-ai/LICENSE | C21: 7e764ea596fddcfc53844d5ac04581d89f75768ea098c6fe798ba6c00e98db83 | D21: 1035 | E21: SDA-AIE-311 | F21: Lab repository | G21: catalog/ai-engineer/SDA-AIE-311-agentic-ai-systems-engineering/labs/tawseel-agentic-ai/LICENSE | H21: Extract | I21: Ready | J21: git
A22: AI Engineer Track/Advanced Agentic AI Systems Engineering/03_Course_Repository/tawseel-agentic-ai.zip | B22: tawseel-agentic-ai/Makefile | C22: e514b8428b3f9185f855be8d082cc68c6e4528fa96a08dad5d888ee3adafef59 | D22: 5375 | E22: SDA-AIE-311 | F22: Lab repository | G22: catalog/ai-engineer/SDA-AIE-311-agentic-ai-systems-engineering/labs/tawseel-agentic-ai/Makefile | H22: Extract | I22: Ready | J22: git
A23: AI Engineer Track/Advanced Agentic AI Systems Engineering/03_Course_Repository/tawseel-agentic-ai.zip | B23: tawseel-agentic-ai/README.md | C23: 7b21e64adf36e2b4412ff0273875aa26d046d173d99d088f34b108ad26a14c25 | D23: 5849 | E23: SDA-AIE-311 | F23: Lab repository | G23: catalog/ai-engineer/SDA-AIE-311-agentic-ai-systems-engineering/labs/tawseel-agentic-ai/README.md | H23: Extract | I23: Ready | J23: git
A24: AI Engineer Track/Advanced Agentic AI Systems Engineering/03_Course_Repository/tawseel-agentic-ai.zip | B24: tawseel-agentic-ai/capstone/README.md | C24: 9eadf3bcba3a2ba25ca1b5f53b74d13e6663e55341c2589208e5757500dbf3b5 | D24: 6235 | E24: SDA-AIE-311 | F24: Lab repository | G24: catalog/ai-engineer/SDA-AIE-311-agentic-ai-systems-engineering/labs/tawseel-agentic-ai/capstone/README.md | H24: Extract | I24: Ready | J24: git
A25: AI Engineer Track/Advanced Agentic AI Systems Engineering/03_Course_Repository/tawseel-agentic-ai.zip | B25: tawseel-agentic-ai/capstone/checklist.md | C25: eb1fd7f48bc92c2f27f3effc1efb6823b0d7aa302a5d1131583beefa2e14a5b1 | D25: 5809 | E25: SDA-AIE-311 | F25: Lab repository | G25: catalog/ai-engineer/SDA-AIE-311-agentic-ai-systems-engineering/labs/tawseel-agentic-ai/capstone/checklist.md | H25: Extract | I25: Ready | J25: git
A26: AI Engineer Track/Advanced Agentic AI Systems Engineering/03_Course_Repository/tawseel-agentic-ai.zip | B26: tawseel-agentic-ai/capstone/grading/instructor_grading_sheet.md | C26: 8d591ee690ed4bec28ee4df03813dfd5b9ae6b61a7e17be6ea96a996a6c6e897 | D26: 3878 | E26: SDA-AIE-311 | F26: Lab repository | G26: catalog/ai-engineer/SDA-AIE-311-agentic-ai-systems-engineering/labs/tawseel-agentic-ai/capstone/grading/instructor_grading_sheet.md | H26: Extract | I26: Ready | J26: git
... A335: AI Engineer Track/Advanced Agentic AI Systems Engineering/03_Course_Repository/tawseel-agentic-ai.zip | B335: tawseel-agentic-ai/tests/unit/test_tools.py | C335: 47b5336351a2d7b09a1c452d403ca19dace372d1975f35bb824b156fc58c8edb | D335: 12438 | E335: SDA-AIE-311 | F335: Lab repository | G335: catalog/ai-engineer/SDA-AIE-311-agentic-ai-systems-engineering/labs/tawseel-agentic-ai/tests/unit/test_tools.py | H335: Extract | I335: Ready | J335: git
A336: AI Engineer Track/Advanced Agentic AI Systems Engineering/INSTRUCTOR_PACKAGE.md | C336: 5ef69eaabb97b570e8c2e7dc7999138d8d7b809554d9cf3b27b8287a8590c1e6 | D336: 223083 | E336: SDA-AIE-311 | F336: Instructor guide | G336: catalog/ai-engineer/SDA-AIE-311-agentic-ai-systems-engineering/instructor-guide.md | H336: Convert | I336: Ready | J336: git | K336: Body preserved verbatim under a governance header
A337: AI Engineer Track/Advanced Agentic AI Systems Engineering/README_START_HERE.md | C337: 60da7b0c7305db264ebd4b86fc563a036afa8652b9e08c81a75f1745bcbc784f | D337: 10546 | E337: SDA-AIE-311 | F337: Programme guide | G337: catalog/ai-engineer/SDA-AIE-311-agentic-ai-systems-engineering/resources/README_START_HERE.md | H337: Migrate | I337: Ready | J337: git
A338: AI Engineer Track/Advanced Agentic AI Systems Engineering/SDA-AIE-311_Program_Package.zip | C338: 8e54a71f16f99be7ac26b0a4e5c549ff74ff722d67a5e0ada5a741dc16f2dd71 | D338: 3049710 | E338: SDA-AIE-311 | F338: Archive | H338: Container | I338: Duplicate | K338: Bundle of the loose files + tawseel repo; only deck_source/ is unique
A339: AI Engineer Track/Advanced Agentic AI Systems Engineering/SDA-AIE-311_Program_Package.zip | B339: SDA-AIE-311_Program_Package/01_Training_Deck/SDA-AIE-311_Agentic_AI_Systems_Engineering_Deck.pdf | C339: 0f677a22fbace5ab416206900145bb94018f1162c17bfe097b3958063b893855 | D339: 2620813 | E339: SDA-AIE-311 | F339: Bundle copy | H339: Duplicate | I339: Duplicate | K339: Same file migrated from the loose folder / tawseel zip
A340: AI Engineer Track/Advanced Agentic AI Systems Engineering/SDA-AIE-311_Program_Package.zip | B340: SDA-AIE-311_Program_Package/01_Training_Deck/SDA-AIE-311_Agentic_AI_Systems_Engineering_Deck.pptx | C340: 7205be374a1ff9475c25efe2a51114323bc10dfd09900c005b3aba97759072f3 | D340: 6972619 | E340: SDA-AIE-311 | F340: Bundle copy | H340: Duplicate | I340: Duplicate | K340: Same file migrated from the loose folder / tawseel zip
A341: AI Engineer Track/Advanced Agentic AI Systems Engineering/SDA-AIE-311_Program_Package.zip | B341: SDA-AIE-311_Program_Package/01_Training_Deck/deck_source/CONTENT_SPEC.md | C341: 80cbc3d00d2b12cc6d94cdca1a2d76f15fb4a12e7e33976d292ce5cb67949a07 | D341: 9361 | E341: SDA-AIE-311 | F341: Slides source | G341: catalog/ai-engineer/SDA-AIE-311-agentic-ai-systems-engineering/slides/deck-source/CONTENT_SPEC.md | H341: Extract | I341: Ready | J341: git | K341: Deck build sources — only unique content of the bundle
A342: AI Engineer Track/Advanced Agentic AI Systems Engineering/SDA-AIE-311_Program_Package.zip | B342: SDA-AIE-311_Program_Package/01_Training_Deck/deck_source/content/00_front.json | C342: 5cb37ba92567da8c6dbb3c17e723e723b02db429a6b775ec34272a461c914938 | D342: 10549 | E342: SDA-AIE-311 | F342: Slides source | G342: catalog/ai-engineer/SDA-AIE-311-agentic-ai-systems-engineering/slides/deck-source/content/00_front.json | H342: Extract | I342: Ready | J342: git | K342: Deck build sources — only unique content of the bundle
A343: AI Engineer Track/Advanced Agentic AI Systems Engineering/SDA-AIE-311_Program_Package.zip | B343: SDA-AIE-311_Program_Package/01_Training_Deck/deck_source/content/10_day1.json | C343: eefdc07fdd71d79b3bffafceb0bc12517cef2c71f44d7cd99ffd7d0454d6bbc8 | D343: 63397 | E343: SDA-AIE-311 | F343: Slides source | G343: catalog/ai-engineer/SDA-AIE-311-agentic-ai-systems-engineering/slides/deck-source/content/10_day1.json | H343: Extract | I343: Ready | J343: git | K343: Deck build sources — only unique content of the bundle
A344: AI Engineer Track/Advanced Agentic AI Systems Engineering/SDA-AIE-311_Program_Package.zip | B344: SDA-AIE-311_Program_Package/01_Training_Deck/deck_source/content/20_day2.json | C344: b9de017df9271f40b619b79a815d6762d0cb6b8a565c540c99a107099b2d0c83 | D344: 61539 | E344: SDA-AIE-311 | F344: Slides source | G344: catalog/ai-engineer/SDA-AIE-311-agentic-ai-systems-engineering/slides/deck-source/content/20_day2.json | H344: Extract | I344: Ready | J344: git | K344: Deck build sources — only unique content of the bundle
A345: AI Engineer Track/Advanced Agentic AI Systems Engineering/SDA-AIE-311_Program_Package.zip | B345: SDA-AIE-311_Program_Package/01_Training_Deck/deck_source/content/30_day3.json | C345: a4d77f3a04f69560552fb3e9af3d020179c28da7d5fd2bb2e274ac90993a6f4a | D345: 75768 | E345: SDA-AIE-311 | F345: Slides source | G345: catalog/ai-engineer/SDA-AIE-311-agentic-ai-systems-engineering/slides/deck-source/content/30_day3.json | H345: Extract | I345: Ready | J345: git | K345: Deck build sources — only unique content of the bundle
A346: AI Engineer Track/Advanced Agentic AI Systems Engineering/SDA-AIE-311_Program_Package.zip | B346: SDA-AIE-311_Program_Package/01_Training_Deck/deck_source/content/40_day4.json | C346: 9bb6c8642f8dd4540238d2f496c659053aa8b49eb69054714039149afd5d6149 | D346: 70534 | E346: SDA-AIE-311 | F346: Slides source | G346: catalog/ai-engineer/SDA-AIE-311-agentic-ai-systems-engineering/slides/deck-source/content/40_day4.json | H346: Extract | I346: Ready | J346: git | K346: Deck build sources — only unique content of the bundle
A347: AI Engineer Track/Advanced Agentic AI Systems Engineering/SDA-AIE-311_Program_Package.zip | B347: SDA-AIE-311_Program_Package/01_Training_Deck/deck_source/content/50_day5.json | C347: a1335ad87a519cb9e299481f23494b0d0cd2c738ab2252e0dec4eabead773219 | D347: 62577 | E347: SDA-AIE-311 | F347: Slides source | G347: catalog/ai-engineer/SDA-AIE-311-agentic-ai-systems-engineering/slides/deck-source/content/50_day5.json | H347: Extract | I347: Ready | J347: git | K347: Deck build sources — only unique content of the bundle
A348: AI Engineer Track/Advanced Agentic AI Systems Engineering/SDA-AIE-311_Program_Package.zip | B348: SDA-AIE-311_Program_Package/01_Training_Deck/deck_source/render.js | C348: 3ca4ba650fd4ba10a7adc51fa38de96a3c2b8ebe039f1c26ff3242e226ca5e92 | D348: 30189 | E348: SDA-AIE-311 | F348: Slides source | G348: catalog/ai-engineer/SDA-AIE-311-agentic-ai-systems-engineering/slides/deck-source/render.js | H348: Extract | I348: Ready | J348: git | K348: Deck build sources — only unique content of the bundle
A349: AI Engineer Track/Advanced Agentic AI Systems Engineering/SDA-AIE-311_Program_Package.zip | B349: SDA-AIE-311_Program_Package/01_Training_Deck/deck_source/theme.js | C349: d308a77099bf6826397af466ce1f6448d510c19eacc8a9769c16d3f31784744e | D349: 1267 | E349: SDA-AIE-311 | F349: Slides source | G349: catalog/ai-engineer/SDA-AIE-311-agentic-ai-systems-engineering/slides/deck-source/theme.js | H349: Extract | I349: Ready | J349: git | K349: Deck build sources — only unique content of the bundle
A350: AI Engineer Track/Advanced Agentic AI Systems Engineering/SDA-AIE-311_Program_Package.zip | B350: SDA-AIE-311_Program_Package/02_Programme_Guides/ASSESSMENT_PACK.md | C350: bab08e0c7cd32cc4825c36d1055c9aa53766a813ed75cd4ab50ccc2a842cf3d9 | D350: 17776 | E350: SDA-AIE-311 | F350: Bundle copy | H350: Duplicate | I350: Duplicate | K350: Same file migrated from the loose folder / tawseel zip
A351: AI Engineer Track/Advanced Agentic AI Systems Engineering/SDA-AIE-311_Program_Package.zip | B351: SDA-AIE-311_Program_Package/02_Programme_Guides/INSTRUCTOR_DELIVERY_GUIDE.md | C351: 8a11598495f6f08dd90759eafcb0bdab2f642bb5195945eac6196e75304630e9 | D351: 27808 | E351: SDA-AIE-311 | F351: Bundle copy | H351: Duplicate | I351: Duplicate | K351: Same file migrated from the loose folder / tawseel zip
A352: AI Engineer Track/Advanced Agentic AI Systems Engineering/SDA-AIE-311_Program_Package.zip | B352: SDA-AIE-311_Program_Package/02_Programme_Guides/PARTICIPANT_HANDBOOK.md | C352: 4119c3df847bc214fd19dc212de3ae01a23f7de865a1074900935e29c0aa469f | D352: 40515 | E352: SDA-AIE-311 | F352: Bundle copy | H352: Duplicate | I352: Duplicate | K352: Same file migrated from the loose folder / tawseel zip
A353: AI Engineer Track/Advanced Agentic AI Systems Engineering/SDA-AIE-311_Program_Package.zip | B353: SDA-AIE-311_Program_Package/02_Programme_Guides/PROGRAMME_OVERVIEW.md | C353: c5ace92269972aeb5a67c0d1fd37288ceca00bee188873bbc53f0f9ddcb1f96b | D353: 9472 | E353: SDA-AIE-311 | F353: Bundle copy | H353: Duplicate | I353: Duplicate | K353: Same file migrated from the loose folder / tawseel zip
A354: AI Engineer Track/Advanced Agentic AI Systems Engineering/SDA-AIE-311_Program_Package.zip | B354: SDA-AIE-311_Program_Package/02_Programme_Guides/RESOURCES.md | C354: 3162834b9a74e95887d884e7a921a2a037f104478c83299ea60af1dd6382d7af | D354: 22183 | E354: SDA-AIE-311 | F354: Bundle copy | H354: Duplicate | I354: Duplicate | K354: Same file migrated from the loose folder / tawseel zip
A355: AI Engineer Track/Advanced Agentic AI Systems Engineering/SDA-AIE-311_Program_Package.zip | B355: SDA-AIE-311_Program_Package/02_Programme_Guides/SETUP_GUIDE.md | C355: d7317ee296db14eb536b3a5fe2e20b1803e22f87f77f9949136601976c3445d8 | D355: 14191 | E355: SDA-AIE-311 | F355: Bundle copy | H355: Duplicate | I355: Duplicate | K355: Same file migrated from the loose folder / tawseel zip
A356: AI Engineer Track/Advanced Agentic AI Systems Engineering/SDA-AIE-311_Program_Package.zip | B356: SDA-AIE-311_Program_Package/02_Programme_Guides/VISUAL_ASSET_BRIEF.md | C356: 14709e59820229251101ebed710b53f1bac65972ab3b3eaf2f4f9920e6643394 | D356: 25085 | E356: SDA-AIE-311 | F356: Bundle copy | H356: Duplicate | I356: Duplicate | K356: Same file migrated from the loose folder / tawseel zip
A357: AI Engineer Track/Advanced Agentic AI Systems Engineering/SDA-AIE-311_Program_Package.zip | B357: SDA-AIE-311_Program_Package/03_Course_Repository/tawseel-agentic-ai/.dockerignore | C357: 23c3bda71253c49714e08e4ef28cfe359f173c44b143fc47c5f9719f31842725 | D357: 590 | E357: SDA-AIE-311 | F357: Bundle copy | H357: Duplicate | I357: Duplicate | K357: Same file migrated from the loose folder / tawseel zip
A358: AI Engineer Track/Advanced Agentic AI Systems Engineering/SDA-AIE-311_Program_Package.zip | B358: SDA-AIE-311_Program_Package/03_Course_Repository/tawseel-agentic-ai/.env.example | C358: 9ce666efe30536bca9f9b66dd60404292a6eb3b9fe8678864d05772dc893fa14 | D358: 2070 | E358: SDA-AIE-311 | F358: Bundle copy | H358: Duplicate | I358: Duplicate | K358: Same file migrated from the loose folder / tawseel zip
A359: AI Engineer Track/Advanced Agentic AI Systems Engineering/SDA-AIE-311_Program_Package.zip | B359: SDA-AIE-311_Program_Package/03_Course_Repository/tawseel-agentic-ai/.github/workflows/ci.yml | C359: 104be6860c06099cdcc0939b55aa9f835e4600322c88aaaf319bc5a143f870a8 | D359: 7675 | E359: SDA-AIE-311 | F359: Bundle copy | H359: Duplicate | I359: Duplicate | K359: Same file migrated from the loose folder / tawseel zip
A360: AI Engineer Track/Advanced Agentic AI Systems Engineering/SDA-AIE-311_Program_Package.zip | B360: SDA-AIE-311_Program_Package/03_Course_Repository/tawseel-agentic-ai/.gitignore | C360: 6d7e9097d691c03851a32f26d0edc7ca6b9b16b50eaa29d0af2e52c8233e5d9e | D360: 1286 | E360: SDA-AIE-311 | F360: Bundle copy | H360: Duplicate | I360: Duplicate | K360: Same file migrated from the loose folder / tawseel zip
A361: AI Engineer Track/Advanced Agentic AI Systems Engineering/SDA-AIE-311_Program_Package.zip | B361: SDA-AIE-311_Program_Package/03_Course_Repository/tawseel-agentic-ai/CONTRIBUTING.md | C361: 5a7600bb500bf3bc302c8eccbc2d130cf5d774836be5ab1283b44b4041d26c04 | D361: 3728 | E361: SDA-AIE-311 | F361: Bundle copy | H361: Duplicate | I361: Duplicate | K361: Same file migrated from the loose folder / tawseel zip
... A678: AI Engineer Track/Advanced Agentic AI Systems Engineering/SDA-AIE-311_Program_Package.zip | B678: SDA-AIE-311_Program_Package/README_START_HERE.md | C678: 60da7b0c7305db264ebd4b86fc563a036afa8652b9e08c81a75f1745bcbc784f | D678: 10546 | E678: SDA-AIE-311 | F678: Bundle copy | H678: Duplicate | I678: Duplicate | K678: Same file migrated from the loose folder / tawseel zip
A679: AI Engineer Track/Applied Machine Learning Foundations/INSTRUCTOR_PACKAGE.md | C679: 8972f8b77fff63152c8953c6c0f59627da7b329b2882ad4721bec26ca645e77d | D679: 218333 | E679: SDA-AIE-111 | F679: Instructor guide | G679: catalog/ai-engineer/SDA-AIE-111-applied-machine-learning-foundations/instructor-guide.md | H679: Convert | I679: Ready | J679: git | K679: Body preserved verbatim under a governance header
A680: AI Engineer Track/Applied Machine Learning Foundations/SDA-AIE-111_Applied_ML_Foundations_Training.pptx | C680: 95384b313011fff741be0cb3b3ec90fa280d0e2d0d73292255880835657b92fc | D680: 547642 | E680: SDA-AIE-111 | F680: Slides | G680: catalog/ai-engineer/SDA-AIE-111-applied-machine-learning-foundations/slides/SDA-AIE-111_Applied_ML_Foundations_Training.pptx | H680: Migrate | I680: Ready | J680: git-lfs
A681: AI Engineer Track/Applied Machine Learning Foundations/SDA-AIE-111_Course_Repo/README.md | C681: 22b01868544a534f351a47ed1ac701fdc351ee8a1db0ecbd3e190030b0e61397 | D681: 3034 | E681: SDA-AIE-111 | F681: Lab repository | G681: catalog/ai-engineer/SDA-AIE-111-applied-machine-learning-foundations/labs/manafeth-course-repo/README.md | H681: Migrate | I681: Ready | J681: git | K681: Participant course repository (notebooks, data, src); solutions/ sub-folder is trainer-only
A682: AI Engineer Track/Applied Machine Learning Foundations/SDA-AIE-111_Course_Repo/RESOURCES.md | C682: d0dbe6afe10dda0b011824ecff68b52cf8ee23c8a28240c3096c4c53f143ad8e | D682: 4190 | E682: SDA-AIE-111 | F682: Lab repository | G682: catalog/ai-engineer/SDA-AIE-111-applied-machine-learning-foundations/labs/manafeth-course-repo/RESOURCES.md | H682: Migrate | I682: Ready | J682: git | K682: Participant course repository (notebooks, data, src); solutions/ sub-folder is trainer-only
A683: AI Engineer Track/Applied Machine Learning Foundations/SDA-AIE-111_Course_Repo/capstone_kit/CAPSTONE_DATASETS.md | C683: 871627840b0e418ba77272cd9335b9b8ba63efc398ca2aec6a502c0d000314fe | D683: 5642 | E683: SDA-AIE-111 | F683: Lab repository | G683: catalog/ai-engineer/SDA-AIE-111-applied-machine-learning-foundations/labs/manafeth-course-repo/capstone_kit/CAPSTONE_DATASETS.md | H683: Migrate | I683: Ready | J683: git | K683: Participant course repository (notebooks, data, src); solutions/ sub-folder is trainer-only
A684: AI Engineer Track/Applied Machine Learning Foundations/SDA-AIE-111_Course_Repo/capstone_kit/prepare_ecommerce_churn.py | C684: 14be083a8aaf3a57779e0eb12554287b8744c21c53350146df45f98793dd5540 | D684: 3867 | E684: SDA-AIE-111 | F684: Lab repository | G684: catalog/ai-engineer/SDA-AIE-111-applied-machine-learning-foundations/labs/manafeth-course-repo/capstone_kit/prepare_ecommerce_churn.py | H684: Migrate | I684: Ready | J684: git | K684: Participant course repository (notebooks, data, src); solutions/ sub-folder is trainer-only
A685: AI Engineer Track/Applied Machine Learning Foundations/SDA-AIE-111_Course_Repo/capstone_kit/prepare_online_retail_ii.py | C685: 6d069376c1e3dcd0b456d416b24fcfb186d9d4bab41402ef9aefe00dfc47731c | D685: 8469 | E685: SDA-AIE-111 | F685: Lab repository | G685: catalog/ai-engineer/SDA-AIE-111-applied-machine-learning-foundations/labs/manafeth-course-repo/capstone_kit/prepare_online_retail_ii.py | H685: Migrate | I685: Ready | J685: git | K685: Participant course repository (notebooks, data, src); solutions/ sub-folder is trainer-only
A686: AI Engineer Track/Applied Machine Learning Foundations/SDA-AIE-111_Course_Repo/case_studies/SDA-AIE-111_Case_Talabat_QuickCommerce.md | C686: a746209afd5d0acb95e72624a441085d16c194fb4122d61b83dc794004e56562 | D686: 9763 | E686: SDA-AIE-111 | F686: Lab repository | G686: catalog/ai-engineer/SDA-AIE-111-applied-machine-learning-foundations/labs/manafeth-course-repo/case_studies/SDA-AIE-111_Case_Talabat_QuickCommerce.md | H686: Migrate | I686: Ready | J686: git | K686: Participant course repository (notebooks, data, src); solutions/ sub-folder is trainer-only
A687: AI Engineer Track/Applied Machine Learning Foundations/SDA-AIE-111_Course_Repo/check_env.ipynb | C687: 73409997d0fa1e6d5339e957bd6f9c2a6d0f68105662a52643aa55a210fd2785 | D687: 3561 | E687: SDA-AIE-111 | F687: Lab repository | G687: catalog/ai-engineer/SDA-AIE-111-applied-machine-learning-foundations/labs/manafeth-course-repo/check_env.ipynb | H687: Migrate | I687: Ready | J687: git | K687: Participant course repository (notebooks, data, src); solutions/ sub-folder is trainer-only
A688: AI Engineer Track/Applied Machine Learning Foundations/SDA-AIE-111_Course_Repo/data/data_dictionary.md | C688: 8c5ea778f294f2f9e95344eea608408f3118da5b0bb9c3543b003345767615ee | D688: 5898 | E688: SDA-AIE-111 | F688: Lab repository | G688: catalog/ai-engineer/SDA-AIE-111-applied-machine-learning-foundations/labs/manafeth-course-repo/data/data_dictionary.md | H688: Migrate | I688: Ready | J688: git | K688: Participant course repository (notebooks, data, src); solutions/ sub-folder is trainer-only
A689: AI Engineer Track/Applied Machine Learning Foundations/SDA-AIE-111_Course_Repo/data/generate_manafeth.py | C689: bb2bedde9f6b72f9cd8cf15f7dd54555ed1307c9a20cdc5a631c7537bb9cf5a3 | D689: 20080 | E689: SDA-AIE-111 | F689: Lab repository | G689: catalog/ai-engineer/SDA-AIE-111-applied-machine-learning-foundations/labs/manafeth-course-repo/data/generate_manafeth.py | H689: Migrate | I689: Ready | J689: git | K689: Participant course repository (notebooks, data, src); solutions/ sub-folder is trainer-only
A690: AI Engineer Track/Applied Machine Learning Foundations/SDA-AIE-111_Course_Repo/data/jeddah_requests_sample.csv | C690: a7407e1a0c5c6f7cb8b7ffd239df37a57822265910400fb203506c7e13d451e4 | D690: 543828 | E690: SDA-AIE-111 | F690: Lab repository | G690: catalog/ai-engineer/SDA-AIE-111-applied-machine-learning-foundations/labs/manafeth-course-repo/data/jeddah_requests_sample.csv | H690: Migrate | I690: Ready | J690: git | K690: Participant course repository (notebooks, data, src); solutions/ sub-folder is trainer-only
A691: AI Engineer Track/Applied Machine Learning Foundations/SDA-AIE-111_Course_Repo/data/jubail_sensors_sample.parquet | C691: b954a7d3415b7b33b523ac988164167ddde3b865a26fb4a51585d50216583fe4 | D691: 103637 | E691: SDA-AIE-111 | F691: Lab repository | G691: catalog/ai-engineer/SDA-AIE-111-applied-machine-learning-foundations/labs/manafeth-course-repo/data/jubail_sensors_sample.parquet | H691: Migrate | I691: Ready | J691: git-lfs | K691: Participant course repository (notebooks, data, src); solutions/ sub-folder is trainer-only
A692: AI Engineer Track/Applied Machine Learning Foundations/SDA-AIE-111_Course_Repo/data/makkah_demand_sample.parquet | C692: 86eb1874669eafda041b8774a8d31a1d0f8aac4fee39dac90034419e92099b9f | D692: 53938 | E692: SDA-AIE-111 | F692: Lab repository | G692: catalog/ai-engineer/SDA-AIE-111-applied-machine-learning-foundations/labs/manafeth-course-repo/data/makkah_demand_sample.parquet | H692: Migrate | I692: Ready | J692: git-lfs | K692: Participant course repository (notebooks, data, src); solutions/ sub-folder is trainer-only
... A723: AI Engineer Track/Applied Machine Learning Foundations/SDA-AIE-111_Course_Repo/src/manafeth/features.py | C723: 373f4beb8b45d7b76789453db6c32086372a2156faf85875297cacbeb876958d | D723: 6257 | E723: SDA-AIE-111 | F723: Lab repository | G723: catalog/ai-engineer/SDA-AIE-111-applied-machine-learning-foundations/labs/manafeth-course-repo/src/manafeth/features.py | H723: Migrate | I723: Ready | J723: git | K723: Participant course repository (notebooks, data, src); solutions/ sub-folder is trainer-only
A724: AI Engineer Track/Applied Machine Learning Foundations/SDA-AIE-111_Manafeth_Data_Package.zip | C724: bf2fbf35f2a3978f01f79dd0272e1bda9f0b5af8d5aa5e7d00c310d23fd563a3 | D724: 18938715 | E724: SDA-AIE-111 | F724: Archive | H724: Container | I724: Ready | K724: Members classified individually
A725: AI Engineer Track/Applied Machine Learning Foundations/SDA-AIE-111_Manafeth_Data_Package.zip | B725: manafeth_data_package/validation_report.txt | C725: e0b0bb36aa170775687a1917e7652fcf59091d787d19d381599922adca9136b1 | D725: 1185 | E725: SDA-AIE-111 | F725: Dataset | H725: Duplicate | I725: Duplicate | K725: Identical to catalog/ai-engineer/SDA-AIE-111-applied-machine-learning-foundations/labs/manafeth-course-repo/data/validation_report.txt (from AI Engineer Track/Applied Machine Learning Foundations/SDA-AIE-111_Course_Repo/data/validation_report.txt)
A726: AI Engineer Track/Applied Machine Learning Foundations/SDA-AIE-111_Manafeth_Data_Package.zip | B726: manafeth_data_package/jeddah_requests_sample.csv | C726: a7407e1a0c5c6f7cb8b7ffd239df37a57822265910400fb203506c7e13d451e4 | D726: 543828 | E726: SDA-AIE-111 | F726: Dataset | H726: Duplicate | I726: Duplicate | K726: Identical to catalog/ai-engineer/SDA-AIE-111-applied-machine-learning-foundations/labs/manafeth-course-repo/data/jeddah_requests_sample.csv (from AI Engineer Track/Applied Machine Learning Foundations/SDA-AIE-111_Course_Repo/data/jeddah_requests_sample.csv)
A727: AI Engineer Track/Applied Machine Learning Foundations/SDA-AIE-111_Manafeth_Data_Package.zip | B727: manafeth_data_package/manafeth_orders.csv | C727: 4b1a40f0e7aa07c897218cdfbfc81811775dcff9255fce3aa15e88808ca0faf1 | D727: 54530328 | E727: SDA-AIE-111 | F727: Dataset (format variant) | H727: Duplicate | I727: Duplicate | K727: CSV export of the migrated .parquet file (≈54 MB); regenerate with data/generate_manafeth.py
A728: AI Engineer Track/Applied Machine Learning Foundations/SDA-AIE-111_Manafeth_Data_Package.zip | B728: manafeth_data_package/shifted_month.parquet | C728: c749fb112ffdd1bdcb768f480c4efb25c4d0837102383b800f1a45b521d3f5f2 | D728: 210622 | E728: SDA-AIE-111 | F728: Dataset | H728: Duplicate | I728: Duplicate | K728: Identical to catalog/ai-engineer/SDA-AIE-111-applied-machine-learning-foundations/labs/manafeth-course-repo/data/shifted_month.parquet (from AI Engineer Track/Applied Machine Learning Foundations/SDA-AIE-111_Course_Repo/data/shifted_month.parquet)
A729: AI Engineer Track/Applied Machine Learning Foundations/SDA-AIE-111_Manafeth_Data_Package.zip | B729: manafeth_data_package/generate_manafeth.py | C729: bb2bedde9f6b72f9cd8cf15f7dd54555ed1307c9a20cdc5a631c7537bb9cf5a3 | D729: 20080 | E729: SDA-AIE-111 | F729: Dataset | H729: Duplicate | I729: Duplicate | K729: Identical to catalog/ai-engineer/SDA-AIE-111-applied-machine-learning-foundations/labs/manafeth-course-repo/data/generate_manafeth.py (from AI Engineer Track/Applied Machine Learning Foundations/SDA-AIE-111_Course_Repo/data/generate_manafeth.py)
A730: AI Engineer Track/Applied Machine Learning Foundations/SDA-AIE-111_Manafeth_Data_Package.zip | B730: manafeth_data_package/manafeth_customers.parquet | C730: e2b6552d8b1c10747df1935fdfafec4666294b8824f3ffb494144799a9eb232b | D730: 978774 | E730: SDA-AIE-111 | F730: Dataset | H730: Duplicate | I730: Duplicate | K730: Identical to catalog/ai-engineer/SDA-AIE-111-applied-machine-learning-foundations/labs/manafeth-course-repo/data/manafeth_customers.parquet (from AI Engineer Track/Applied Machine Learning Foundations/SDA-AIE-111_Course_Repo/data/manafeth_customers.parquet)
A731: AI Engineer Track/Applied Machine Learning Foundations/SDA-AIE-111_Manafeth_Data_Package.zip | B731: manafeth_data_package/markabat_listings_sample.csv | C731: a2489998669d9f16cbc1a462a4fa30467fcaa27d3fd401645b23a77a120d2279 | D731: 117371 | E731: SDA-AIE-111 | F731: Dataset | H731: Duplicate | I731: Duplicate | K731: Identical to catalog/ai-engineer/SDA-AIE-111-applied-machine-learning-foundations/labs/manafeth-course-repo/data/markabat_listings_sample.csv (from AI Engineer Track/Applied Machine Learning Foundations/SDA-AIE-111_Course_Repo/data/markabat_listings_sample.csv)
A732: AI Engineer Track/Applied Machine Learning Foundations/SDA-AIE-111_Manafeth_Data_Package.zip | B732: manafeth_data_package/manafeth_customers.csv | C732: 263f5dee5211b623016c2cbd6e3348327c7041d1b9936b3c86942e13cacc1d04 | D732: 4730035 | E732: SDA-AIE-111 | F732: Dataset (format variant) | H732: Duplicate | I732: Duplicate | K732: CSV export of the migrated .parquet file (≈54 MB); regenerate with data/generate_manafeth.py
A733: AI Engineer Track/Applied Machine Learning Foundations/SDA-AIE-111_Manafeth_Data_Package.zip | B733: manafeth_data_package/makkah_demand_sample.parquet | C733: 86eb1874669eafda041b8774a8d31a1d0f8aac4fee39dac90034419e92099b9f | D733: 53938 | E733: SDA-AIE-111 | F733: Dataset | H733: Duplicate | I733: Duplicate | K733: Identical to catalog/ai-engineer/SDA-AIE-111-applied-machine-learning-foundations/labs/manafeth-course-repo/data/makkah_demand_sample.parquet (from AI Engineer Track/Applied Machine Learning Foundations/SDA-AIE-111_Course_Repo/data/makkah_demand_sample.parquet)
A734: AI Engineer Track/Applied Machine Learning Foundations/SDA-AIE-111_Manafeth_Data_Package.zip | B734: manafeth_data_package/manafeth_orders.parquet | C734: df8c4e4feae76190492d17664c4d8e7405201655ff7e2048e6ddbcf687465b9b | D734: 10100791 | E734: SDA-AIE-111 | F734: Dataset | H734: Duplicate | I734: Duplicate | K734: Identical to catalog/ai-engineer/SDA-AIE-111-applied-machine-learning-foundations/labs/manafeth-course-repo/data/manafeth_orders.parquet (from AI Engineer Track/Applied Machine Learning Foundations/SDA-AIE-111_Course_Repo/data/manafeth_orders.parquet)
A735: AI Engineer Track/Applied Machine Learning Foundations/SDA-AIE-111_Manafeth_Data_Package.zip | B735: manafeth_data_package/validate_data.py | C735: 3ea297f4ac8249324a6da3ac498a961213377b59f2d0d3a3b94403643cae1e0d | D735: 8558 | E735: SDA-AIE-111 | F735: Dataset | H735: Duplicate | I735: Duplicate | K735: Identical to catalog/ai-engineer/SDA-AIE-111-applied-machine-learning-foundations/labs/manafeth-course-repo/data/validate_data.py (from AI Engineer Track/Applied Machine Learning Foundations/SDA-AIE-111_Course_Repo/data/validate_data.py)
A736: AI Engineer Track/Applied Machine Learning Foundations/SDA-AIE-111_Manafeth_Data_Package.zip | B736: manafeth_data_package/data_dictionary.md | C736: 8c5ea778f294f2f9e95344eea608408f3118da5b0bb9c3543b003345767615ee | D736: 5898 | E736: SDA-AIE-111 | F736: Dataset | H736: Duplicate | I736: Duplicate | K736: Identical to catalog/ai-engineer/SDA-AIE-111-applied-machine-learning-foundations/labs/manafeth-course-repo/data/data_dictionary.md (from AI Engineer Track/Applied Machine Learning Foundations/SDA-AIE-111_Course_Repo/data/data_dictionary.md)
A737: AI Engineer Track/Applied Machine Learning Foundations/SDA-AIE-111_Manafeth_Data_Package.zip | B737: manafeth_data_package/jubail_sensors_sample.parquet | C737: b954a7d3415b7b33b523ac988164167ddde3b865a26fb4a51585d50216583fe4 | D737: 103637 | E737: SDA-AIE-111 | F737: Dataset | H737: Duplicate | I737: Duplicate | K737: Identical to catalog/ai-engineer/SDA-AIE-111-applied-machine-learning-foundations/labs/manafeth-course-repo/data/jubail_sensors_sample.parquet (from AI Engineer Track/Applied Machine Learning Foundations/SDA-AIE-111_Course_Repo/data/jubail_sensors_sample.parquet)
A738: AI Engineer Track/Applied Machine Learning Foundations/data_dictionary.md | C738: 8c5ea778f294f2f9e95344eea608408f3118da5b0bb9c3543b003345767615ee | D738: 5898 | E738: SDA-AIE-111 | F738: Dataset documentation | H738: Duplicate | I738: Duplicate | K738: Identical to labs/manafeth-course-repo/data/data_dictionary.md
A739: AI Engineer Track/Applied Natural Language Processing/Bayan_Data_Catalog.xlsx | C739: 1c6588e99978ec989d4553d9574217c024ffe38f356a34ffa73e65539cec00fd | D739: 10135 | E739: SDA-AIE-211 | F739: Dataset documentation | G739: catalog/ai-engineer/SDA-AIE-211-natural-language-processing-with-transformers/datasets/Bayan_Data_Catalog.xlsx | H739: Migrate | I739: Ready | J739: git-lfs
A740: AI Engineer Track/Applied Natural Language Processing/Bayan_Data_Catalog.xlsx.inspect.ndjson | C740: 15d2c60753678e27e69f9504417459f9fb37befa2b93c5e1d803a852e4eb8a31 | D740: 84049 | E740: SDA-AIE-211 | F740: Tool artefact | H740: Exclude | I740: Obsolete | K740: PPTX/XLSX inspection dump generated by an authoring tool
A741: AI Engineer Track/Applied Natural Language Processing/Bayan_Training_Data.zip | C741: 06bab3426d64f304c5ef9ac4b1b888bf1d127c4e36695f3e5e70d98e84a4f97f | D741: 627854 | E741: SDA-AIE-211 | F741: Archive | H741: Container | I741: Ready | K741: Members classified individually
A742: AI Engineer Track/Applied Natural Language Processing/Bayan_Training_Data.zip | B742: Bayan_Training_Data/data/arabic_normalize_golden.csv | C742: 48c14ec97e89a59a2d0836e243ce3e89c279c921fb3e469bd169db8350377101 | D742: 2133 | E742: SDA-AIE-211 | F742: Dataset | G742: catalog/ai-engineer/SDA-AIE-211-natural-language-processing-with-transformers/datasets/bayan-training-data/data/arabic_normalize_golden.csv | H742: Extract | I742: Ready | J742: git
A743: AI Engineer Track/Applied Natural Language Processing/Bayan_Training_Data.zip | B743: Bayan_Training_Data/data/bayan_cases.csv | C743: 13dc7df7eed8f1be3d741495f91a063999e6c5372ca3d987d661222843d77f62 | D743: 3828296 | E743: SDA-AIE-211 | F743: Dataset | G743: catalog/ai-engineer/SDA-AIE-211-natural-language-processing-with-transformers/datasets/bayan-training-data/data/bayan_cases.csv | H743: Extract | I743: Ready | J743: git
A744: AI Engineer Track/Applied Natural Language Processing/Bayan_Training_Data.zip | B744: Bayan_Training_Data/data/bayan_feedback.csv | C744: 6ecc9edc4a30440fe5d04ea45d04346715b97d6f3600faea06980d947fc0ae15 | D744: 1982863 | E744: SDA-AIE-211 | F744: Dataset | G744: catalog/ai-engineer/SDA-AIE-211-natural-language-processing-with-transformers/datasets/bayan-training-data/data/bayan_feedback.csv | H744: Extract | I744: Ready | J744: git
A745: AI Engineer Track/Applied Natural Language Processing/Bayan_Training_Data.zip | B745: Bayan_Training_Data/data/bayan_ner.conll | C745: 4d0adae95c44d92ea81c08ffdb2763772f3bd6602a4d94485e9fa4acab070784 | D745: 568107 | E745: SDA-AIE-211 | F745: Dataset | G745: catalog/ai-engineer/SDA-AIE-211-natural-language-processing-with-transformers/datasets/bayan-training-data/data/bayan_ner.conll | H745: Extract | I745: Ready | J745: git
A746: AI Engineer Track/Applied Natural Language Processing/Bayan_Training_Data.zip | B746: Bayan_Training_Data/data/bayan_ner_segmented.conll | C746: eeef78201352e8f0f1a6b20ac9c9453994341f25ec5004377d907b4633378fec | D746: 576107 | E746: SDA-AIE-211 | F746: Dataset | G746: catalog/ai-engineer/SDA-AIE-211-natural-language-processing-with-transformers/datasets/bayan-training-data/data/bayan_ner_segmented.conll | H746: Extract | I746: Ready | J746: git
A747: AI Engineer Track/Applied Natural Language Processing/Bayan_Training_Data.zip | B747: Bayan_Training_Data/data/bayan_qa.json | C747: d5a51b8213f5c5b2caeec6b2b8e741c64c2597f500ee39a196e4727cbcbee564 | D747: 200545 | E747: SDA-AIE-211 | F747: Dataset | G747: catalog/ai-engineer/SDA-AIE-211-natural-language-processing-with-transformers/datasets/bayan-training-data/data/bayan_qa.json | H747: Extract | I747: Ready | J747: git
A748: AI Engineer Track/Applied Natural Language Processing/Bayan_Training_Data.zip | B748: Bayan_Training_Data/data/bayan_queries.jsonl | C748: d4d6b56e6d6d6aa37810e2c809ecf0c796b4f464431989d0030a83b25715989f | D748: 32482 | E748: SDA-AIE-211 | F748: Dataset | G748: catalog/ai-engineer/SDA-AIE-211-natural-language-processing-with-transformers/datasets/bayan-training-data/data/bayan_queries.jsonl | H748: Extract | I748: Security Concern | J748: git | K748: Contains Saudi phone/national-ID patterns; pack LICENSE states the data is synthetic — confirm and keep the SYNTHETIC notice
A749: AI Engineer Track/Applied Natural Language Processing/Bayan_Training_Data.zip | B749: Bayan_Training_Data/data/bayan_raw_sample.csv | C749: 95239dff1ddbabbf6efa1d1c5b36046e3c70981640e47c629d767b4b5a493433 | D749: 34015 | E749: SDA-AIE-211 | F749: Dataset | G749: catalog/ai-engineer/SDA-AIE-211-natural-language-processing-with-transformers/datasets/bayan-training-data/data/bayan_raw_sample.csv | H749: Extract | I749: Security Concern | J749: git | K749: Contains Saudi phone/national-ID patterns; pack LICENSE states the data is synthetic — confirm and keep the SYNTHETIC notice
A750: AI Engineer Track/Applied Natural Language Processing/Bayan_Training_Data.zip | B750: Bayan_Training_Data/data/behavioural_templates.csv | C750: 7f8097d6f9191a71ca794ee427fbf363d1781526cc87a80776c5002531b41036 | D750: 39819 | E750: SDA-AIE-211 | F750: Dataset | G750: catalog/ai-engineer/SDA-AIE-211-natural-language-processing-with-transformers/datasets/bayan-training-data/data/behavioural_templates.csv | H750: Extract | I750: Ready | J750: git
A751: AI Engineer Track/Applied Natural Language Processing/Bayan_Training_Data.zip | B751: Bayan_Training_Data/data/bench_mix.npy | C751: 6cb4fa52c183a54022b23c79cd8b56134779c94e503fcba41edf00da34ba6865 | D751: 768128 | E751: SDA-AIE-211 | F751: Dataset | G751: catalog/ai-engineer/SDA-AIE-211-natural-language-processing-with-transformers/datasets/bayan-training-data/data/bench_mix.npy | H751: Extract | I751: Ready | J751: git-lfs
A752: AI Engineer Track/Applied Natural Language Processing/Bayan_Training_Data.zip | B752: Bayan_Training_Data/data/bm25_baseline_results.jsonl | C752: 7120a1034c8b4de6975daf6e48db56f5232aaa7e0ca1e9214d7ce8a6430400b2 | D752: 15450 | E752: SDA-AIE-211 | F752: Dataset | G752: catalog/ai-engineer/SDA-AIE-211-natural-language-processing-with-transformers/datasets/bayan-training-data/data/bm25_baseline_results.jsonl | H752: Extract | I752: Ready | J752: git
A753: AI Engineer Track/Applied Natural Language Processing/Bayan_Training_Data.zip | B753: Bayan_Training_Data/data/load_test_config.yaml | C753: fa2782e5ae7cea10aaf460dd17b1cc42f9cbdab3a24b2680a7347a20320dd6aa | D753: 103 | E753: SDA-AIE-211 | F753: Dataset | G753: catalog/ai-engineer/SDA-AIE-211-natural-language-processing-with-transformers/datasets/bayan-training-data/data/load_test_config.yaml | H753: Extract | I753: Ready | J753: git
A754: AI Engineer Track/Applied Natural Language Processing/Bayan_Training_Data.zip | B754: Bayan_Training_Data/data/pii_test_set.csv | C754: ec71d5b0e6debf6a4c1773f235dc289af4699f4293296d89ceeac15267d255fb | D754: 5886 | E754: SDA-AIE-211 | F754: Dataset | G754: catalog/ai-engineer/SDA-AIE-211-natural-language-processing-with-transformers/datasets/bayan-training-data/data/pii_test_set.csv | H754: Extract | I754: Security Concern | J754: git | K754: Contains Saudi phone/national-ID patterns; pack LICENSE states the data is synthetic — confirm and keep the SYNTHETIC notice
...
